airflow/providers/amazon/__init__.py
airflow/providers/amazon/get_provider_info.py
airflow/providers/amazon/version_compat.py
airflow/providers/amazon/aws/__init__.py
airflow/providers/amazon/aws/exceptions.py
airflow/providers/amazon/aws/assets/__init__.py
airflow/providers/amazon/aws/assets/s3.py
airflow/providers/amazon/aws/auth_manager/__init__.py
airflow/providers/amazon/aws/auth_manager/aws_auth_manager.py
airflow/providers/amazon/aws/auth_manager/constants.py
airflow/providers/amazon/aws/auth_manager/user.py
airflow/providers/amazon/aws/auth_manager/avp/__init__.py
airflow/providers/amazon/aws/auth_manager/avp/entities.py
airflow/providers/amazon/aws/auth_manager/avp/facade.py
airflow/providers/amazon/aws/auth_manager/avp/schema.json
airflow/providers/amazon/aws/auth_manager/cli/__init__.py
airflow/providers/amazon/aws/auth_manager/cli/avp_commands.py
airflow/providers/amazon/aws/auth_manager/datamodels/__init__.py
airflow/providers/amazon/aws/auth_manager/datamodels/login.py
airflow/providers/amazon/aws/auth_manager/routes/__init__.py
airflow/providers/amazon/aws/auth_manager/routes/login.py
airflow/providers/amazon/aws/bundles/__init__.py
airflow/providers/amazon/aws/bundles/s3.py
airflow/providers/amazon/aws/cli/__init__.py
airflow/providers/amazon/aws/cli/definition.py
airflow/providers/amazon/aws/executors/Dockerfile
airflow/providers/amazon/aws/executors/__init__.py
airflow/providers/amazon/aws/executors/aws_lambda/__init__.py
airflow/providers/amazon/aws/executors/aws_lambda/lambda_executor.py
airflow/providers/amazon/aws/executors/aws_lambda/utils.py
airflow/providers/amazon/aws/executors/aws_lambda/docker/Dockerfile
airflow/providers/amazon/aws/executors/aws_lambda/docker/__init__.py
airflow/providers/amazon/aws/executors/aws_lambda/docker/app.py
airflow/providers/amazon/aws/executors/batch/__init__.py
airflow/providers/amazon/aws/executors/batch/batch_executor.py
airflow/providers/amazon/aws/executors/batch/batch_executor_config.py
apache_airflow_providers_amazon-9.20.0.dist-info/entry_points.txt
apache_airflow_providers_amazon-9.20.0.dist-info/licenses/LICENSE
apache_airflow_providers_amazon-9.20.0.dist-info/licenses/NOTICE
apache_airflow_providers_amazon-9.20.0.dist-info/WHEEL
apache_airflow_providers_amazon-9.20.0.dist-info/METADATA
apache_airflow_providers_amazon-9.20.0.dist-info/RECORD
