Metadata-Version: 2.4
Name: apache-airflow-providers-amazon
Version: 9.20.0
Summary: Provider package apache-airflow-providers-amazon for Apache Airflow
Keywords: airflow-provider,amazon,airflow,integration
Author-email: Apache Software Foundation <dev@airflow.apache.org>
Maintainer-email: Apache Software Foundation <dev@airflow.apache.org>
Requires-Python: >=3.10
License-Expression: Apache-2.0
Classifier: Development Status :: 5 - Production/Stable
Classifier: Environment :: Console
Classifier: Environment :: Web Environment
Classifier: Intended Audience :: Developers
Classifier: Intended Audience :: System Administrators
Classifier: Framework :: Apache Airflow
Classifier: Framework :: Apache Airflow :: Provider
Classifier: Programming Language :: Python :: 3.10
Classifier: Programming Language :: Python :: 3.11
Classifier: Programming Language :: Python :: 3.12
Classifier: Programming Language :: Python :: 3.13
Classifier: Topic :: System :: Monitoring
License-File: LICENSE
License-File: NOTICE
Requires-Dist: apache-airflow>=2.11.0
Requires-Dist: apache-airflow-providers-common-compat>=1.12.0
Requires-Dist: apache-airflow-providers-common-sql>=1.27.0
Requires-Dist: apache-airflow-providers-http
Requires-Dist: boto3>=1.37.2
Requires-Dist: botocore>=1.37.2
Requires-Dist: inflection>=0.5.1
Requires-Dist: watchtower>=3.3.1,<4
Requires-Dist: jsonpath_ng>=1.5.3
Requires-Dist: redshift_connector>=2.1.3
Requires-Dist: asgiref>=2.3.0
Requires-Dist: PyAthena>=3.10.0
Requires-Dist: jmespath>=0.7.0
Requires-Dist: sagemaker-studio>=1.0.9
Requires-Dist: pydynamodb>=0.7.5; python_version >= '3.13'
Requires-Dist: sqlean.py>=3.47.0; python_version >= '3.13'
Requires-Dist: marshmallow>=3
Requires-Dist: aiobotocore[boto3]>=2.21.1 ; extra == "aiobotocore"
Requires-Dist: apache-airflow-providers-apache-hive ; extra == "apache-hive"
Requires-Dist: apache-airflow-providers-cncf-kubernetes>=7.2.0 ; extra == "cncf-kubernetes"
Requires-Dist: apache-airflow-providers-common-messaging>=2.0.0 ; extra == "common-messaging"
Requires-Dist: apache-airflow-providers-exasol ; extra == "exasol"
Requires-Dist: apache-airflow-providers-fab>=2.2.0 ; extra == "fab" and ( python_version < '3.13')
Requires-Dist: apache-airflow-providers-ftp ; extra == "ftp"
Requires-Dist: apache-airflow-providers-google ; extra == "google"
Requires-Dist: apache-airflow-providers-imap ; extra == "imap"
Requires-Dist: apache-airflow-providers-microsoft-azure ; extra == "microsoft-azure"
Requires-Dist: apache-airflow-providers-mongo ; extra == "mongo"
Requires-Dist: apache-airflow-providers-openlineage>=2.3.0 ; extra == "openlineage"
Requires-Dist: pandas>=2.1.2 ; extra == "pandas" and ( python_version <"3.13")
Requires-Dist: pandas>=2.2.3 ; extra == "pandas" and ( python_version >="3.13")
Requires-Dist: python3-saml>=1.16.0 ; extra == "python3-saml" and ( python_version < '3.13')
Requires-Dist: xmlsec>=1.3.14 ; extra == "python3-saml" and ( python_version < '3.13')
Requires-Dist: lxml>=6.0.0 ; extra == "python3-saml" and ( python_version < '3.13')
Requires-Dist: s3fs>=2023.10.0 ; extra == "s3fs"
Requires-Dist: apache-airflow-providers-salesforce ; extra == "salesforce"
Requires-Dist: sqlalchemy>=1.4.49 ; extra == "sqlalchemy"
Requires-Dist: apache-airflow-providers-ssh ; extra == "ssh"
Requires-Dist: apache-airflow-providers-standard ; extra == "standard"
Project-URL: Bug Tracker, https://github.com/apache/airflow/issues
Project-URL: Changelog, https://airflow.apache.org/docs/apache-airflow-providers-amazon/9.20.0/changelog.html
Project-URL: Documentation, https://airflow.apache.org/docs/apache-airflow-providers-amazon/9.20.0
Project-URL: Mastodon, https://fosstodon.org/@airflow
Project-URL: Slack Chat, https://s.apache.org/airflow-slack
Project-URL: Source Code, https://github.com/apache/airflow
Project-URL: YouTube, https://www.youtube.com/channel/UCSXwxpWZQ7XZ1WL3wqevChA/
Provides-Extra: aiobotocore
Provides-Extra: apache-hive
Provides-Extra: cncf-kubernetes
Provides-Extra: common-messaging
Provides-Extra: exasol
Provides-Extra: fab
Provides-Extra: ftp
Provides-Extra: google
Provides-Extra: imap
Provides-Extra: microsoft-azure
Provides-Extra: mongo
Provides-Extra: openlineage
Provides-Extra: pandas
Provides-Extra: python3-saml
Provides-Extra: s3fs
Provides-Extra: salesforce
Provides-Extra: sqlalchemy
Provides-Extra: ssh
Provides-Extra: standard
